./.gitignore
./.python-version
./LICENSE
./PKG-INFO
./README.md
./pyproject.toml
./uv.lock
./.github/workflows/publish.yml
./xf/__init__.py
./xf/main.py
./xf/commands/__init__.py
./xf/commands/base.py
./xf/commands/dbt.py
./xf/commands/profiling.py
./xf/commands/pytest.py
./xf/commands/sqlmesh.py
./xf/core/__init__.py
./xf/core/console.py
./xf/core/isolation.py
./xf/core/magics.py
./xf/core/shell_mode.py
./xf/core/startup.py
./xf/core/styling.py
./xf/utils/__init__.py
./xf/utils/env.py
./xf/utils/paths.py
./xf/utils/profiling.py
xf_cli-0.0.6.dist-info/METADATA
xf_cli-0.0.6.dist-info/WHEEL
xf_cli-0.0.6.dist-info/entry_points.txt
xf_cli-0.0.6.dist-info/licenses/LICENSE
xf_cli-0.0.6.dist-info/RECORD
