Metadata-Version: 2.4
Name: xf-cli
Version: 0.0.6
Summary: XF makes repeated python commands faster through import preloading
Author-email: Justin Leder <justin@turntable.so>
License-File: LICENSE
Requires-Python: >=3.9
Requires-Dist: ipython>=8.18.1
Requires-Dist: pickleshare>=0.7.5
Requires-Dist: pyinstrument>=5.0.0
Requires-Dist: rich>=13.9.4
Requires-Dist: tomlkit>=0.13.2
Requires-Dist: typer>=0.15.1
Requires-Dist: uv>=0.5.11
Provides-Extra: profile
Requires-Dist: pyinstrument>=5.0.0; extra == 'profile'
Provides-Extra: pytest
Requires-Dist: pytest>=8.3.4; extra == 'pytest'
Provides-Extra: pytest-django
Requires-Dist: pytest-django>=4.9.0; extra == 'pytest-django'
Requires-Dist: pytest>=8.3.4; extra == 'pytest-django'
